epub2txt/__init__.py
epub2txt/__main__.py
epub2txt/browse_filename.py
epub2txt/epub2txt.py
epub2txt/gen_filename.py
epub2txt-0.1.5.dist-info/entry_points.txt
epub2txt-0.1.5.dist-info/LICENSE
epub2txt-0.1.5.dist-info/WHEEL
epub2txt-0.1.5.dist-info/METADATA
epub2txt-0.1.5.dist-info/RECORD
