Metadata-Version: 2.1
Name: epub2txt
Version: 0.1.5
Summary: Convert epub to txt with additonal utils
Home-page: https://github.com/ffreemt/epub2txt
License: MIT
Author: freemt
Requires-Python: >=3.8,<4.0
Classifier: License :: OSI Approved :: MIT License
Classifier: Programming Language :: Python :: 3
Classifier: Programming Language :: Python :: 3.8
Classifier: Programming Language :: Python :: 3.9
Classifier: Programming Language :: Python :: 3.10
Requires-Dist: absl-py (>=0.11.0,<0.12.0)
Requires-Dist: ebooklib (>=0.17.1,<0.18.0)
Requires-Dist: httpx
Requires-Dist: logzero (>=1.6.3,<2.0.0)
Requires-Dist: tqdm (>=4.56.0,<5.0.0)
Project-URL: Repository, https://github.com/ffreemt/epub2txt
